IOT_GD/modport.py
IOT_GD/moacon.py
IOT_GD/__init__.py
IOT_GD/mcp3208.py
IOT_GD-1.0.8.dist-info/DESCRIPTION.rst
IOT_GD-1.0.8.dist-info/METADATA
IOT_GD-1.0.8.dist-info/RECORD
IOT_GD-1.0.8.dist-info/metadata.json
IOT_GD-1.0.8.dist-info/top_level.txt
IOT_GD-1.0.8.dist-info/WHEEL
