Metadata-Version: 2.0
Name: IOT-GD
Version: 1.0.8
Summary: IoT. You can read moacon modules (Modbus communication - cubloc.com) and mcp3208 - 8 channel 12Bit ADC from Rpi 3 and others.
Home-page: https://github.com/sergiosanchezs/IOT-GD
Author: Sergio Sanchez, Ruben Morales
Author-email: sergio.sanchezs@ingenieros.com
License: Mozilla Public License Version 2.0
Keywords: IOT_GD moacon ADC modbus rs-485 spi Analog
Platform: UNKNOWN
Classifier: Development Status :: 4 - Beta
Classifier: Development Status :: 5 - Production/Stable
Classifier: Intended Audience :: Education
Classifier: Intended Audience :: Developers
Classifier: Topic :: System :: Hardware :: Hardware Drivers
Classifier: License :: OSI Approved :: Mozilla Public License 2.0 (MPL 2.0)
Classifier: Programming Language :: Python :: 2
Classifier: Programming Language :: Python :: 2.6
Classifier: Programming Language :: Python :: 2.7
Classifier: Operating System :: POSIX :: Linux
Classifier: Natural Language :: English
